my_foo/__init__.py
fooDemoDC-0.0.3.dist-info/LICENSE
fooDemoDC-0.0.3.dist-info/METADATA
fooDemoDC-0.0.3.dist-info/WHEEL
fooDemoDC-0.0.3.dist-info/top_level.txt
fooDemoDC-0.0.3.dist-info/RECORD
